setup.py
imhotep_jshint/__init__.py
imhotep_jshint/plugin.py
imhotep_jshint.egg-info/PKG-INFO
imhotep_jshint.egg-info/SOURCES.txt
imhotep_jshint.egg-info/dependency_links.txt
imhotep_jshint.egg-info/entry_points.txt
imhotep_jshint.egg-info/top_level.txt