Metadata-Version: 1.0
Name: imhotep-jshint
Version: 0.0.1
Summary: An imhotep plugin for jshint validation
Home-page: https://github.com/justinabrahms/imhotep_jshint
Author: Justin Abrahms
Author-email: justin@abrah.ms
License: MIT
Platform: UNKNOWN
